partycool/__init__.py
partycool/partycool.py
partycool/tests/__init__.py
partycool/tests/partycool.py
partycool/tests/test_partycool.py
partycool-0.0.4.dist-info/LICENSE
partycool-0.0.4.dist-info/METADATA
partycool-0.0.4.dist-info/WHEEL
partycool-0.0.4.dist-info/top_level.txt
partycool-0.0.4.dist-info/RECORD
