Metadata-Version: 2.1
Name: partycool
Version: 0.0.4
Summary: Particle Size Analysis Package for All Microscopy Images
Home-page: https://github.com/yamanmy/partycool
Author: Muammer yaman, Ximin Hu, Margherita Taddei, Yangwei Shi
Author-email: author@example.com
License: UNKNOWN
Platform: UNKNOWN
Classifier: Programming Language :: Python :: 3
Classifier: License :: OSI Approved :: MIT License
Classifier: Operating System :: OS Independent
Requires-Python: >=3.6
